httpyexpect/__init__.py
httpyexpect/base_exception.py
httpyexpect/models.py
httpyexpect/validation.py
httpyexpect/client/__init__.py
httpyexpect/client/custom_types.py
httpyexpect/client/exceptions.py
httpyexpect/client/mapping.py
httpyexpect/client/translator.py
httpyexpect/server/__init__.py
httpyexpect/server/exceptions.py
httpyexpect/server/handlers/__init__.py
httpyexpect/server/handlers/fastapi_.py
scripts/__init__.py
scripts/get_package_name.py
scripts/license_checker.py
scripts/update_http_exception_schema.py
scripts/update_template_files.py
scripts/script_utils/__init__.py
scripts/script_utils/cli.py
scripts/script_utils/fastapi_app_location.py
tests/fixtures/__init__.py
tests/fixtures/utils.py
tests/integration/__init__.py
tests/integration/test_client.py
tests/integration/test_fastapi.py
tests/integration/fixtures/__init__.py
tests/integration/fixtures/utils.py
tests/unit/__init__.py
tests/unit/test_mapping.py
tests/unit/test_models.py
tests/unit/test_server_exceptions.py
tests/unit/test_translator.py
tests/unit/test_validation.py
tests/unit/fixtures/__init__.py
tests/unit/fixtures/utils.py
httpyexpect-0.2.7.dist-info/LICENSE
httpyexpect-0.2.7.dist-info/METADATA
httpyexpect-0.2.7.dist-info/WHEEL
httpyexpect-0.2.7.dist-info/top_level.txt
httpyexpect-0.2.7.dist-info/RECORD
