Metadata-Version: 2.1
Name: httpyexpect
Version: 0.2.7
Summary: An opinionated way to translate server side HTTP errors to the client side.
Home-page: https://github.com/ghga-de/httpyexpect
Author: German Human Genome Phenome Archive (GHGA)
Author-email: contact@ghga.de
License: Apache 2.0
Classifier: Operating System :: POSIX :: Linux
Classifier: Programming Language :: Python :: 3.9
Classifier: License :: OSI Approved :: Apache Software License
Classifier: Topic :: Internet :: WWW/HTTP :: HTTP Servers
Requires-Python: >=3.9
License-File: LICENSE
Provides-Extra: all
Requires-Dist: fastapi (>=0.96.0) ; extra == 'all'
Requires-Dist: datamodel-code-generator (==0.19.0) ; extra == 'all'
Provides-Extra: dev
Requires-Dist: datamodel-code-generator (==0.19.0) ; extra == 'dev'
Provides-Extra: fastapi
Requires-Dist: fastapi (>=0.96.0) ; extra == 'fastapi'
